ZlapiNormal/__init__.py
ZlapiNormal/core.py
ZlapiNormal-1.0.2.dist-info/METADATA
ZlapiNormal-1.0.2.dist-info/WHEEL
ZlapiNormal-1.0.2.dist-info/top_level.txt
ZlapiNormal-1.0.2.dist-info/RECORD
