Metadata-Version: 2.1
Name: ZlapiNormal
Version: 1.0.2
Summary: Library ZaloData
Home-page: 
Author: Lâm Minh Phú
Author-email: zalochatbot@gmail.com
Classifier: Programming Language :: Python :: 3
Classifier: License :: OSI Approved :: MIT License
Classifier: Operating System :: OS Independent
Requires-Dist: zlapi
Provides-Extra: telegram
Requires-Dist: python-telegram-bot; extra == "telegram"
Requires-Dist: telebot; extra == "telegram"
